vcsvgenie/__init__.py
vcsvgenie/dc_waveform.py
vcsvgenie/read.py
vcsvgenie/transient_waveform.py
vcsvgenie/waveform.py
vcsvgenie-2.2.6.dist-info/licenses/LICENSE
vcsvgenie-2.2.6.dist-info/METADATA
vcsvgenie-2.2.6.dist-info/WHEEL
vcsvgenie-2.2.6.dist-info/top_level.txt
vcsvgenie-2.2.6.dist-info/RECORD
