Metadata-Version: 2.4
Name: vcsvgenie
Version: 2.2.6
Summary: Programmatic Interpretations of Cadence Virtuoso Waveform VCSV files
Author-email: Jake Peterson <jake612@duck.com>
Project-URL: Homepage, https://github.com/fsharp4/vcsvgenie
Project-URL: Issues, https://github.com/fsharp4/vcsvgenie/issues
Classifier: Programming Language :: Python :: 3
Classifier: License :: OSI Approved :: GNU General Public License v3 (GPLv3)
Classifier: Operating System :: OS Independent
Requires-Python: >=3.11
License-File: LICENSE
Requires-Dist: numpy<3.0.0,>=2.0.0
Requires-Dist: matplotlib<4.0.0,>=3.9.0
Requires-Dist: pandas<3.0.0,>=2.2.0
Requires-Dist: scikit-learn<2.0.0,>=1.5.0
Requires-Dist: sortedcontainers<3.0.0,>=2.4.0
Provides-Extra: dev
Requires-Dist: pytest>=7.0; extra == "dev"
Requires-Dist: black>=22.0; extra == "dev"
Requires-Dist: jupyter; extra == "dev"
Requires-Dist: notebook; extra == "dev"
Requires-Dist: ipython; extra == "dev"
Requires-Dist: tqdm>=4.66.0; extra == "dev"
Dynamic: license-file
